pybrightsign/__init__.py
pybrightsign/server.py
pybrightsign/sessionwithurlbase.py
pybrightsign/.idea/.gitignore
pybrightsign/.idea/dataSources.local.xml
pybrightsign/.idea/icon.png
pybrightsign/.idea/icon_dark.png
pybrightsign/.idea/misc.xml
pybrightsign/.idea/modules.xml
pybrightsign/.idea/pybrightsign.iml
pybrightsign/.idea/vcs.xml
pybrightsign/.idea/workspace.xml
pybrightsign/.idea/inspectionProfiles/Project_Default.xml
pybrightsign/.idea/inspectionProfiles/profiles_settings.xml
pybrightsign/__pycache__/__init__.cpython-39.pyc
pybrightsign/__pycache__/server.cpython-39.pyc
pybrightsign/__pycache__/sessionwithurlbase.cpython-39.pyc
pybrightsign-0.9.4.dist-info/METADATA
pybrightsign-0.9.4.dist-info/WHEEL
pybrightsign-0.9.4.dist-info/top_level.txt
pybrightsign-0.9.4.dist-info/RECORD
