Metadata-Version: 2.1
Name: pybrightsign
Version: 0.9.4
Summary: BrightSign APIs for humans.  Python module to simplify using the BrightSign BSN/BSNEE API.
Home-page: https://github.com/pointw-dev/pybrightsign
Author: Michael Ottoson
Author-email: michael@pointw.com
License: MIT
Platform: UNKNOWN
Classifier: Development Status :: 4 - Beta
Classifier: License :: OSI Approved :: MIT License
Classifier: Programming Language :: Python :: 3
Classifier: Operating System :: OS Independent
Classifier: Intended Audience :: Developers
Classifier: Topic :: Adaptive Technologies
Classifier: Topic :: Utilities
Requires-Dist: requests
Requires-Dist: oauthlib (==2.1.0)
Requires-Dist: requests-oauthlib (==1.1.0)
